{
	"animations": [
		{
			"offsets": [
				0,
				0
			],
			"loop": false,
			"fps": 10,
			"anim": "singRIGHT",
			"indices": [],
			"name": "right"
		},
		{
			"offsets": [
				4,
				0
			],
			"loop": false,
			"fps": 10,
			"anim": "singUP",
			"indices": [],
			"name": "up"
		},
		{
			"offsets": [
				0,
				0
			],
			"loop": false,
			"fps": 10,
			"anim": "singLEFT",
			"indices": [],
			"name": "left"
		},
		{
			"offsets": [
				0,
				0
			],
			"loop": false,
			"fps": 10,
			"anim": "singDOWN",
			"indices": [],
			"name": "down"
		},
		{
			"loop": false,
			"offsets": [
				0,
				0
			],
			"anim": "idle",
			"fps": 10,
			"name": "Idle",
			"indices": []
		},
		{
			"loop": false,
			"offsets": [
				0,
				0
			],
			"anim": "fuck",
			"fps": 10,
			"name": "FUCK",
			"indices": []
		}
	],
	"no_antialiasing": true,
	"image": "characters/hardoween/pino",
	"position": [
		-39,
		367
	],
	"healthicon": "peppino",
	"flip_x": true,
	"healthbar_colors": [
		255,
		255,
		255
	],
	"camera_position": [
		530,
		-469
	],
	"sing_duration": 4,
	"scale": 6
}