{
	"storyName": "",
	"hideFreeplay": false,
	"weekBackground": "stage",
	"freeplayColor": [
		146,
		113,
		253
	],
	"weekBefore": "",
	"startUnlocked": true,
	"weekCharacters": [
		"",
		"",
		""
	],
	"songs": [
		[
			"Chills",
			"spooky",
			[
				0,
				0,
				0
			]
		],
		[
			"Full-Body Amputation",
			"sp9",
			[
				0,
				0,
				0
			]
		],
		[
			"Septicemia",
			"sp9-boss",
			[
				0,
				0,
				0
			]
		],
		[
			"Antagonized",
			"protag",
			[
				0,
				0,
				0
			]
		]
	],
	"hideStoryMode": false,
	"weekName": ""
}