<?xml version="1.0" encoding="utf-8"?>
<TextureAtlas imagePath="BFBirdDeadFlip.png">
	<!-- Created with Adobe Animate version 21.0.0.35450 -->
	<!-- http://www.adobe.com/products/animate.html -->
	<SubTexture name="BF_FlipAlive instância 10000" x="0" y="0" width="412" height="393"/>
	<SubTexture name="BF_FlipAlive instância 10001" x="422" y="0" width="412" height="393"/>
	<SubTexture name="BF_FlipAlive instância 10002" x="844" y="0" width="412" height="393"/>
	<SubTexture name="BF_FlipAlive instância 10003" x="1266" y="0" width="412" height="393"/>
	<SubTexture name="BF_FlipAlive instância 10004" x="1688" y="0" width="412" height="393"/>
	<SubTexture name="BF_FlipAlive instância 10005" x="2110" y="0" width="412" height="393"/>
	<SubTexture name="BF_FlipAlive instância 10006" x="2532" y="0" width="412" height="393"/>
	<SubTexture name="BF_FlipAlive instância 10007" x="2954" y="0" width="412" height="393"/>
	<SubTexture name="BF_FlipAlive instância 10008" x="3376" y="0" width="412" height="393"/>
	<SubTexture name="BF_FlipAlive instância 10009" x="0" y="403" width="412" height="393"/>
	<SubTexture name="BF_FlipAlive instância 10010" x="422" y="403" width="412" height="393"/>
	<SubTexture name="BF_FlipAlive instância 10011" x="844" y="403" width="412" height="393"/>
	<SubTexture name="BF_FlipAlive instância 10012" x="1266" y="403" width="412" height="393"/>
	<SubTexture name="BF_FlipAlive instância 10013" x="1688" y="403" width="412" height="393"/>
	<SubTexture name="BF_FlipAlive instância 10014" x="2110" y="403" width="412" height="393"/>
	<SubTexture name="BF_FlipAlive instância 10015" x="2532" y="403" width="412" height="393"/>
	<SubTexture name="BF_FlipAlive instância 10016" x="2954" y="403" width="412" height="393"/>
	<SubTexture name="BF_FlipAlive instância 10017" x="3376" y="403" width="412" height="393"/>
	<SubTexture name="BF_FlipAlive instância 10018" x="0" y="806" width="412" height="393"/>
	<SubTexture name="BF_FlipAlive instância 10019" x="422" y="806" width="412" height="393"/>
	<SubTexture name="BF_FlipAlive instância 10020" x="844" y="806" width="412" height="393"/>
	<SubTexture name="BF_FlipAlive instância 10021" x="1266" y="806" width="412" height="393"/>
	<SubTexture name="BF_FlipAlive instância 10022" x="1688" y="806" width="412" height="393"/>
	<SubTexture name="BF_FlipAlive instância 10023" x="2110" y="806" width="412" height="393"/>
	<SubTexture name="BF_FlipAlive instância 10024" x="2532" y="806" width="412" height="393"/>
	<SubTexture name="BF_FlipAlive instância 10025" x="2532" y="806" width="412" height="393"/>
	<SubTexture name="BF_FlipAlive instância 10026" x="2532" y="806" width="412" height="393"/>
	<SubTexture name="BF_FlipAlive instância 10027" x="2532" y="806" width="412" height="393"/>
	<SubTexture name="BF_FlipAlive instância 10028" x="2532" y="806" width="412" height="393"/>
	<SubTexture name="BF_FlipAlive instância 10029" x="2532" y="806" width="412" height="393"/>
	<SubTexture name="BF_FlipAlive instância 10030" x="2532" y="806" width="412" height="393"/>
	<SubTexture name="BF_FlipAlive instância 10031" x="2532" y="806" width="412" height="393"/>
	<SubTexture name="BF_FlipAlive instância 10032" x="2532" y="806" width="412" height="393"/>
	<SubTexture name="BF_FlipAlive instância 10033" x="2532" y="806" width="412" height="393"/>
	<SubTexture name="BF_FlipAlive instância 10034" x="2532" y="806" width="412" height="393"/>
	<SubTexture name="BF_FlipDead instância 10000" x="2954" y="806" width="454" height="395"/>
	<SubTexture name="BF_FlipDead instância 10001" x="3418" y="806" width="454" height="395"/>
	<SubTexture name="BF_FlipDead instância 10002" x="0" y="1211" width="454" height="395"/>
	<SubTexture name="BF_FlipDead instância 10003" x="0" y="1211" width="454" height="395"/>
	<SubTexture name="BF_FlipDead instância 10004" x="0" y="1211" width="454" height="395"/>
	<SubTexture name="BF_FlipDead instância 10005" x="0" y="1211" width="454" height="395"/>
	<SubTexture name="BF_FlipDead instância 10006" x="0" y="1211" width="454" height="395"/>
	<SubTexture name="BF_FlipDead instância 10007" x="0" y="1211" width="454" height="395"/>
	<SubTexture name="BF_FlipDead instância 10008" x="0" y="1211" width="454" height="395"/>
	<SubTexture name="BF_FlipDead instância 10009" x="0" y="1211" width="454" height="395"/>
	<SubTexture name="BF_FlipDead instância 10010" x="0" y="1211" width="454" height="395"/>
	<SubTexture name="BF_FlipDead instância 10011" x="0" y="1211" width="454" height="395"/>
	<SubTexture name="BF_FlipDead instância 10012" x="0" y="1211" width="454" height="395"/>
	<SubTexture name="BF_FlipDead instância 10013" x="0" y="1211" width="454" height="395"/>
	<SubTexture name="BF_FlipDead instância 10014" x="0" y="1211" width="454" height="395"/>
	<SubTexture name="BF_FlipDead instância 10015" x="0" y="1211" width="454" height="395"/>
	<SubTexture name="BF_FlipDead instância 10016" x="0" y="1211" width="454" height="395"/>
	<SubTexture name="BF_FlipDead instância 10017" x="0" y="1211" width="454" height="395"/>
	<SubTexture name="BF_FlipDead instância 10018" x="0" y="1211" width="454" height="395"/>
	<SubTexture name="BF_FlipDead instância 10019" x="0" y="1211" width="454" height="395"/>
	<SubTexture name="BF_FlipDead instância 10020" x="0" y="1211" width="454" height="395"/>
	<SubTexture name="BF_FlipDead instância 10021" x="0" y="1211" width="454" height="395"/>
	<SubTexture name="BF_FlipDead instância 10022" x="0" y="1211" width="454" height="395"/>
	<SubTexture name="BF_FlipDead instância 10023" x="0" y="1211" width="454" height="395"/>
	<SubTexture name="BF_FlipDead instância 10024" x="464" y="1211" width="454" height="395"/>
	<SubTexture name="BF_FlipDead instância 10025" x="928" y="1211" width="454" height="395"/>
	<SubTexture name="BF_FlipDead instância 10026" x="1392" y="1211" width="454" height="395"/>
	<SubTexture name="BF_FlipDead instância 10027" x="1856" y="1211" width="454" height="395"/>
	<SubTexture name="BF_FlipDead instância 10028" x="2320" y="1211" width="454" height="395"/>
	<SubTexture name="BF_FlipDead instância 10029" x="2784" y="1211" width="454" height="395"/>
	<SubTexture name="BF_FlipDead instância 10030" x="3248" y="1211" width="454" height="395"/>
	<SubTexture name="BF_FlipDead instância 10031" x="0" y="1616" width="454" height="395"/>
	<SubTexture name="BF_FlipDead instância 10032" x="464" y="1616" width="454" height="395"/>
	<SubTexture name="BF_FlipDead instância 10033" x="928" y="1616" width="454" height="395"/>
	<SubTexture name="BF_FlipDead instância 10034" x="1392" y="1616" width="454" height="395"/>
	<SubTexture name="BF_FlipDead instância 10035" x="1856" y="1616" width="454" height="395"/>
	<SubTexture name="BF_FlipDead instância 10036" x="2320" y="1616" width="454" height="395"/>
	<SubTexture name="BF_FlipDead instância 10037" x="2784" y="1616" width="454" height="395"/>
	<SubTexture name="BF_FlipDead instância 10038" x="3248" y="1616" width="454" height="395"/>
	<SubTexture name="BF_FlipDead instância 10039" x="0" y="2021" width="454" height="395"/>
	<SubTexture name="BF_FlipDead instância 10040" x="464" y="2021" width="454" height="395"/>
	<SubTexture name="BF_FlipDead instância 10041" x="928" y="2021" width="454" height="395"/>
	<SubTexture name="BF_FlipDead instância 10042" x="1392" y="2021" width="454" height="395"/>
	<SubTexture name="BF_FlipDead instância 10043" x="1856" y="2021" width="454" height="395"/>
	<SubTexture name="BF_FlipDead instância 10044" x="2320" y="2021" width="454" height="395"/>
	<SubTexture name="BF_FlipDead instância 10045" x="2320" y="2021" width="454" height="395"/>
	<SubTexture name="BF_FlipDead instância 10046" x="2784" y="2021" width="454" height="395"/>
	<SubTexture name="BF_FlipDead instância 10047" x="2784" y="2021" width="454" height="395"/>
	<SubTexture name="BF_FlipDead instância 10048" x="2784" y="2021" width="454" height="395"/>
	<SubTexture name="BF_FlipDead instância 10049" x="2784" y="2021" width="454" height="395"/>
	<SubTexture name="BF_FlipDead instância 10050" x="2784" y="2021" width="454" height="395"/>
	<SubTexture name="BF_FlipDead instância 10051" x="3248" y="2021" width="454" height="395"/>
	<SubTexture name="BF_FlipDead instância 10052" x="3248" y="2021" width="454" height="395"/>
	<SubTexture name="BF_FlipDead instância 10053" x="0" y="2426" width="454" height="395"/>
	<SubTexture name="BF_FlipDead instância 10054" x="464" y="2426" width="454" height="395"/>
	<SubTexture name="BF_FlipDead instância 10055" x="464" y="2426" width="454" height="395"/>
	<SubTexture name="BF_FlipDead instância 10056" x="928" y="2426" width="454" height="395"/>
	<SubTexture name="BF_FlipDead instância 10057" x="928" y="2426" width="454" height="395"/>
	<SubTexture name="BF_FlipDead instância 10058" x="1392" y="2426" width="454" height="395"/>
	<SubTexture name="BF_FlipDead instância 10059" x="1392" y="2426" width="454" height="395"/>
	<SubTexture name="BF_FlipDead instância 10060" x="1392" y="2426" width="454" height="395"/>
	<SubTexture name="BF_FlipDead instância 10061" x="1392" y="2426" width="454" height="395"/>
	<SubTexture name="BF_FlipDead instância 10062" x="1392" y="2426" width="454" height="395"/>
	<SubTexture name="BF_FlipDead instância 10063" x="1392" y="2426" width="454" height="395"/>
	<SubTexture name="BF_FlipDead instância 10064" x="1392" y="2426" width="454" height="395"/>
	<SubTexture name="BF_FlipDead instância 10065" x="1392" y="2426" width="454" height="395"/>
	<SubTexture name="BF_FlipDead instância 10066" x="1392" y="2426" width="454" height="395"/>
	<SubTexture name="BF_FlipDead instância 10067" x="1392" y="2426" width="454" height="395"/>
	<SubTexture name="BF_FlipDead instância 10068" x="1392" y="2426" width="454" height="395"/>
	<SubTexture name="BF_FlipDead instância 10069" x="1392" y="2426" width="454" height="395"/>
	<SubTexture name="BF_FlipDead instância 10070" x="1392" y="2426" width="454" height="395"/>
	<SubTexture name="BF_FlipDead instância 10071" x="1392" y="2426" width="454" height="395"/>
	<SubTexture name="BF_FlipDead instância 10072" x="1392" y="2426" width="454" height="395"/>
	<SubTexture name="BF_FlipDead instância 10073" x="1392" y="2426" width="454" height="395"/>
	<SubTexture name="BF_FlipDead instância 10074" x="1392" y="2426" width="454" height="395"/>
	<SubTexture name="BF_FlipLoop instância 10000" x="1856" y="2426" width="334" height="341"/>
	<SubTexture name="BF_FlipLoop instância 10001" x="1856" y="2426" width="334" height="341"/>
	<SubTexture name="BF_FlipLoop instância 10002" x="2200" y="2426" width="334" height="341"/>
	<SubTexture name="BF_FlipLoop instância 10003" x="2200" y="2426" width="334" height="341"/>
	<SubTexture name="BF_FlipLoop instância 10004" x="2544" y="2426" width="334" height="341"/>
	<SubTexture name="BF_FlipLoop instância 10005" x="2544" y="2426" width="334" height="341"/>
	<SubTexture name="BF_FlipLoop instância 10006" x="2888" y="2426" width="334" height="341"/>
	<SubTexture name="BF_FlipLoop instância 10007" x="2888" y="2426" width="334" height="341"/>
	<SubTexture name="BF_FlipLoop instância 10008" x="2888" y="2426" width="334" height="341"/>
	<SubTexture name="BF_FlipLoop instância 10009" x="2888" y="2426" width="334" height="341"/>
	<SubTexture name="BF_FlipLoop instância 10010" x="2888" y="2426" width="334" height="341"/>
	<SubTexture name="BF_FlipLoop instância 10011" x="2888" y="2426" width="334" height="341"/>
	<SubTexture name="BF_FlipLoop instância 10012" x="2888" y="2426" width="334" height="341"/>
	<SubTexture name="BF_FlipLoop instância 10013" x="2888" y="2426" width="334" height="341"/>
	<SubTexture name="BF_FlipLoop instância 10014" x="2888" y="2426" width="334" height="341"/>
	<SubTexture name="BF_FlipLoop instância 10015" x="2888" y="2426" width="334" height="341"/>
	<SubTexture name="BF_FlipLoop instância 10016" x="2888" y="2426" width="334" height="341"/>
</TextureAtlas>
