<?xml version="1.0" encoding="utf-8"?>
<TextureAtlas imagePath="pizza-tower-ost-bonus-pizza-mayhem.png">
  <!-- silly funny :3 -->
  <SubTexture name="load00" x="452" y="1857" width="72" height="67" frameX="-25" frameY="-125" frameWidth="200" frameHeight="200"/>
  <SubTexture name="load01" x="1552" y="1853" width="72" height="67" frameX="-25" frameY="-125" frameWidth="200" frameHeight="200"/>
  <SubTexture name="load02" x="1352" y="1776" width="71" height="68" frameX="-26" frameY="-124" frameWidth="200" frameHeight="200"/>
  <SubTexture name="load03" x="452" y="1857" width="72" height="67" frameX="-25" frameY="-125" frameWidth="200" frameHeight="200"/>
  <SubTexture name="load04" x="1552" y="1853" width="72" height="67" frameX="-25" frameY="-125" frameWidth="200" frameHeight="200"/>
  <SubTexture name="load05" x="1352" y="1776" width="71" height="68" frameX="-26" frameY="-124" frameWidth="200" frameHeight="200"/>
  <SubTexture name="load06" x="452" y="1857" width="72" height="67" frameX="-25" frameY="-125" frameWidth="200" frameHeight="200"/>
  <SubTexture name="load07" x="1552" y="1853" width="72" height="67" frameX="-25" frameY="-125" frameWidth="200" frameHeight="200"/>
  <SubTexture name="load08" x="1352" y="1776" width="71" height="68" frameX="-26" frameY="-124" frameWidth="200" frameHeight="200"/>
  <SubTexture name="load09" x="452" y="1857" width="72" height="67" frameX="-25" frameY="-125" frameWidth="200" frameHeight="200"/>
  <SubTexture name="load010" x="1552" y="1853" width="72" height="67" frameX="-25" frameY="-125" frameWidth="200" frameHeight="200"/>
  <SubTexture name="load011" x="1352" y="1776" width="71" height="68" frameX="-26" frameY="-124" frameWidth="200" frameHeight="200"/>
  <SubTexture name="load012" x="452" y="1857" width="72" height="67" frameX="-25" frameY="-125" frameWidth="200" frameHeight="200"/>
  <SubTexture name="load013" x="1552" y="1853" width="72" height="67" frameX="-25" frameY="-125" frameWidth="200" frameHeight="200"/>
  <SubTexture name="load014" x="1352" y="1776" width="71" height="68" frameX="-26" frameY="-124" frameWidth="200" frameHeight="200"/>
  <SubTexture name="load015" x="452" y="1857" width="72" height="67" frameX="-25" frameY="-125" frameWidth="200" frameHeight="200"/>
  <SubTexture name="load016" x="1552" y="1853" width="72" height="67" frameX="-25" frameY="-125" frameWidth="200" frameHeight="200"/>
  <SubTexture name="load017" x="1352" y="1776" width="71" height="68" frameX="-26" frameY="-124" frameWidth="200" frameHeight="200"/>
  <SubTexture name="load018" x="452" y="1857" width="72" height="67" frameX="-25" frameY="-125" frameWidth="200" frameHeight="200"/>
  <SubTexture name="load019" x="1552" y="1853" width="72" height="67" frameX="-25" frameY="-125" frameWidth="200" frameHeight="200"/>
  <SubTexture name="load020" x="1352" y="1776" width="71" height="68" frameX="-26" frameY="-124" frameWidth="200" frameHeight="200"/>
  <SubTexture name="load021" x="452" y="1857" width="72" height="67" frameX="-25" frameY="-125" frameWidth="200" frameHeight="200"/>
  <SubTexture name="load022" x="1552" y="1853" width="72" height="67" frameX="-25" frameY="-125" frameWidth="200" frameHeight="200"/>
  <SubTexture name="load023" x="1352" y="1776" width="71" height="68" frameX="-26" frameY="-124" frameWidth="200" frameHeight="200"/>
  <SubTexture name="load024" x="452" y="1857" width="72" height="67" frameX="-25" frameY="-125" frameWidth="200" frameHeight="200"/>
  <SubTexture name="load025" x="1552" y="1853" width="72" height="67" frameX="-25" frameY="-125" frameWidth="200" frameHeight="200"/>
  <SubTexture name="load026" x="1352" y="1776" width="71" height="68" frameX="-26" frameY="-124" frameWidth="200" frameHeight="200"/>
  <SubTexture name="load027" x="452" y="1857" width="72" height="67" frameX="-25" frameY="-125" frameWidth="200" frameHeight="200"/>
  <SubTexture name="load028" x="1552" y="1853" width="72" height="67" frameX="-25" frameY="-125" frameWidth="200" frameHeight="200"/>
  <SubTexture name="load029" x="974" y="812" width="130" height="192" frameX="-26" frameY="-0" frameWidth="200" frameHeight="200"/>
  <SubTexture name="load030" x="1678" y="811" width="138" height="192" frameX="-22" frameY="-0" frameWidth="200" frameHeight="200"/>
  <SubTexture name="load031" x="2056" y="800" width="138" height="192" frameX="-22" frameY="-0" frameWidth="200" frameHeight="200"/>
  <SubTexture name="load032" x="2065" y="491" width="135" height="192" frameX="-26" frameY="-0" frameWidth="200" frameHeight="200"/>
  <SubTexture name="load033" x="400" y="949" width="137" height="176" frameX="-25" frameY="-16" frameWidth="200" frameHeight="200"/>
  <SubTexture name="load034" x="1504" y="959" width="137" height="153" frameX="-25" frameY="-39" frameWidth="200" frameHeight="200"/>
  <SubTexture name="load035" x="200" y="814" width="137" height="134" frameX="-25" frameY="-58" frameWidth="200" frameHeight="200"/>
  <SubTexture name="load036" x="1036" y="1385" width="138" height="115" frameX="-25" frameY="-77" frameWidth="200" frameHeight="200"/>
  <SubTexture name="load037" x="1135" y="1085" width="147" height="103" frameX="-16" frameY="-89" frameWidth="200" frameHeight="200"/>
  <SubTexture name="load038" x="1046" y="1625" width="143" height="68" frameX="-20" frameY="-124" frameWidth="200" frameHeight="200"/>
  <SubTexture name="load039" x="981" y="1757" width="140" height="64" frameX="-21" frameY="-128" frameWidth="200" frameHeight="200"/>
  <SubTexture name="load040" x="981" y="1693" width="143" height="64" frameX="-21" frameY="-128" frameWidth="200" frameHeight="200"/>
  <SubTexture name="load041" x="1281" y="1648" width="149" height="64" frameX="-21" frameY="-128" frameWidth="200" frameHeight="200"/>
  <SubTexture name="load042" x="235" y="1653" width="147" height="64" frameX="-21" frameY="-128" frameWidth="200" frameHeight="200"/>
  <SubTexture name="load043" x="382" y="1687" width="144" height="64" frameX="-21" frameY="-128" frameWidth="200" frameHeight="200"/>
  <SubTexture name="load044" x="1641" y="1003" width="142" height="75" frameX="-21" frameY="-117" frameWidth="200" frameHeight="200"/>
  <SubTexture name="load045" x="465" y="1602" width="140" height="85" frameX="-21" frameY="-107" frameWidth="200" frameHeight="200"/>
  <SubTexture name="load046" x="1843" y="1598" width="141" height="88" frameX="-21" frameY="-104" frameWidth="200" frameHeight="200"/>
  <SubTexture name="load047" x="605" y="1615" width="141" height="82" frameX="-21" frameY="-110" frameWidth="200" frameHeight="200"/>
  <SubTexture name="load048" x="961" y="1004" width="142" height="73" frameX="-21" frameY="-119" frameWidth="200" frameHeight="200"/>
  <SubTexture name="load049" x="1835" y="1686" width="142" height="65" frameX="-21" frameY="-127" frameWidth="200" frameHeight="200"/>
  <SubTexture name="load050" x="1615" y="1727" width="143" height="64" frameX="-21" frameY="-128" frameWidth="200" frameHeight="200"/>
  <SubTexture name="load051" x="92" y="1649" width="143" height="66" frameX="-21" frameY="-128" frameWidth="200" frameHeight="200"/>
  <SubTexture name="load052" x="746" y="1669" width="143" height="65" frameX="-21" frameY="-128" frameWidth="200" frameHeight="200"/>
  <SubTexture name="load053" x="235" y="1717" width="143" height="64" frameX="-21" frameY="-128" frameWidth="200" frameHeight="200"/>
  <SubTexture name="load054" x="526" y="1697" width="143" height="64" frameX="-21" frameY="-128" frameWidth="200" frameHeight="200"/>
  <SubTexture name="load055" x="92" y="1715" width="143" height="64" frameX="-21" frameY="-128" frameWidth="200" frameHeight="200"/>
  <SubTexture name="load056" x="1281" y="1712" width="143" height="64" frameX="-21" frameY="-128" frameWidth="200" frameHeight="200"/>
  <SubTexture name="load057" x="378" y="1751" width="142" height="64" frameX="-21" frameY="-128" frameWidth="200" frameHeight="200"/>
  <SubTexture name="load058" x="669" y="1734" width="142" height="64" frameX="-21" frameY="-128" frameWidth="200" frameHeight="200"/>
  <SubTexture name="load059" x="1758" y="1751" width="141" height="64" frameX="-21" frameY="-128" frameWidth="200" frameHeight="200"/>
  <SubTexture name="load060" x="1124" y="1752" width="141" height="64" frameX="-21" frameY="-128" frameWidth="200" frameHeight="200"/>
  <SubTexture name="load061" x="1511" y="1791" width="138" height="62" frameX="-23" frameY="-130" frameWidth="200" frameHeight="200"/>
  <SubTexture name="load062" x="1478" y="1112" width="157" height="62" frameX="-5" frameY="-130" frameWidth="200" frameHeight="200"/>
  <SubTexture name="load063" x="884" y="1591" width="162" height="78" frameX="-0" frameY="-114" frameWidth="200" frameHeight="200"/>
  <SubTexture name="load064" x="1321" y="1188" width="156" height="95" frameX="-7" frameY="-97" frameWidth="200" frameHeight="200"/>
  <SubTexture name="load065" x="1235" y="1558" width="156" height="90" frameX="-7" frameY="-102" frameWidth="200" frameHeight="200"/>
  <SubTexture name="load066" x="1078" y="1535" width="157" height="90" frameX="-7" frameY="-102" frameWidth="200" frameHeight="200"/>
  <SubTexture name="load067" x="921" y="1500" width="157" height="91" frameX="-7" frameY="-101" frameWidth="200" frameHeight="200"/>
  <SubTexture name="load068" x="1374" y="1466" width="157" height="92" frameX="-7" frameY="-100" frameWidth="200" frameHeight="200"/>
  <SubTexture name="load069" x="627" y="1525" width="157" height="90" frameX="-7" frameY="-102" frameWidth="200" frameHeight="200"/>
  <SubTexture name="load070" x="316" y="1472" width="157" height="91" frameX="-7" frameY="-101" frameWidth="200" frameHeight="200"/>
  <SubTexture name="load071" x="159" y="1466" width="157" height="92" frameX="-7" frameY="-100" frameWidth="200" frameHeight="200"/>
  <SubTexture name="load072" x="1078" y="1535" width="157" height="90" frameX="-7" frameY="-102" frameWidth="200" frameHeight="200"/>
  <SubTexture name="load073" x="1687" y="1509" width="156" height="91" frameX="-7" frameY="-101" frameWidth="200" frameHeight="200"/>
  <SubTexture name="load074" x="1531" y="1466" width="156" height="92" frameX="-7" frameY="-100" frameWidth="200" frameHeight="200"/>
  <SubTexture name="load075" x="310" y="1563" width="155" height="90" frameX="-7" frameY="-102" frameWidth="200" frameHeight="200"/>
  <SubTexture name="load076" x="0" y="1557" width="155" height="91" frameX="-7" frameY="-101" frameWidth="200" frameHeight="200"/>
  <SubTexture name="load077" x="473" y="1510" width="154" height="92" frameX="-7" frameY="-100" frameWidth="200" frameHeight="200"/>
  <SubTexture name="load078" x="1391" y="1558" width="155" height="90" frameX="-7" frameY="-102" frameWidth="200" frameHeight="200"/>
  <SubTexture name="load079" x="155" y="1558" width="155" height="91" frameX="-7" frameY="-101" frameWidth="200" frameHeight="200"/>
  <SubTexture name="load080" x="1531" y="1466" width="156" height="92" frameX="-7" frameY="-100" frameWidth="200" frameHeight="200"/>
  <SubTexture name="load081" x="1235" y="1558" width="156" height="90" frameX="-7" frameY="-102" frameWidth="200" frameHeight="200"/>
  <SubTexture name="load082" x="1896" y="1507" width="157" height="91" frameX="-7" frameY="-101" frameWidth="200" frameHeight="200"/>
  <SubTexture name="load083" x="159" y="1466" width="157" height="92" frameX="-7" frameY="-100" frameWidth="200" frameHeight="200"/>
  <SubTexture name="load084" x="758" y="1435" width="163" height="90" frameX="-7" frameY="-102" frameWidth="200" frameHeight="200"/>
  <SubTexture name="load085" x="0" y="1466" width="159" height="91" frameX="-7" frameY="-101" frameWidth="200" frameHeight="200"/>
  <SubTexture name="load086" x="917" y="1191" width="193" height="100" frameX="-7" frameY="-100" frameWidth="200" frameHeight="200"/>
  <SubTexture name="load087" x="724" y="1189" width="193" height="102" frameX="-7" frameY="-98" frameWidth="200" frameHeight="200"/>
  <SubTexture name="load088" x="774" y="944" width="187" height="139" frameX="-13" frameY="-61" frameWidth="200" frameHeight="200"/>
  <SubTexture name="load089" x="200" y="949" width="200" height="128" frameX="-0" frameY="-72" frameWidth="200" frameHeight="200"/>
  <SubTexture name="load090" x="1304" y="959" width="200" height="123" frameX="-0" frameY="-77" frameWidth="200" frameHeight="200"/>
  <SubTexture name="load091" x="1816" y="953" width="200" height="125" frameX="-0" frameY="-75" frameWidth="200" frameHeight="200"/>
  <SubTexture name="load092" x="374" y="812" width="200" height="137" frameX="-0" frameY="-63" frameWidth="200" frameHeight="200"/>
  <SubTexture name="load093" x="774" y="812" width="200" height="132" frameX="-0" frameY="-68" frameWidth="200" frameHeight="200"/>
  <SubTexture name="load094" x="0" y="830" width="200" height="132" frameX="-0" frameY="-62" frameWidth="200" frameHeight="200"/>
  <SubTexture name="load095" x="400" y="1125" width="105" height="39" frameX="-0" frameY="-61" frameWidth="200" frameHeight="200"/>
  <SubTexture name="load096" x="1816" y="854" width="45" height="34" frameX="-51" frameY="-59" frameWidth="200" frameHeight="200"/>
  <SubTexture name="load097" x="337" y="842" width="36" height="24" frameX="-50" frameY="-61" frameWidth="200" frameHeight="200"/>
  <SubTexture name="load098" x="2099" y="783" width="21" height="16" frameX="-52" frameY="-55" frameWidth="200" frameHeight="200"/>
  <SubTexture name="load099" x="2120" y="783" width="17" height="17" frameX="-49" frameY="-44" frameWidth="200" frameHeight="200"/>
  <SubTexture name="load0100" x="387" y="184" width="10" height="14" frameX="-42" frameY="-35" frameWidth="200" frameHeight="200"/>
  <SubTexture name="load0101" x="397" y="184" width="1" height="1" frameX="-0" frameY="-0" frameWidth="200" frameHeight="200"/>
  <SubTexture name="load0102" x="1829" y="1886" width="200" height="10" frameX="-0" frameY="-190" frameWidth="200" frameHeight="200"/>
  <SubTexture name="load0103" x="87" y="1877" width="200" height="26" frameX="-0" frameY="-174" frameWidth="200" frameHeight="200"/>
  <SubTexture name="load0104" x="1352" y="1853" width="200" height="40" frameX="-0" frameY="-160" frameWidth="200" frameHeight="200"/>
  <SubTexture name="load0105" x="1984" y="1635" width="200" height="56" frameX="-0" frameY="-144" frameWidth="200" frameHeight="200"/>
  <SubTexture name="load0106" x="1174" y="1462" width="200" height="73" frameX="-0" frameY="-127" frameWidth="200" frameHeight="200"/>
  <SubTexture name="load0107" x="1508" y="1290" width="200" height="88" frameX="-0" frameY="-112" frameWidth="200" frameHeight="200"/>
  <SubTexture name="load0108" x="200" y="1077" width="200" height="104" frameX="-0" frameY="-96" frameWidth="200" frameHeight="200"/>
  <SubTexture name="load0109" x="0" y="962" width="200" height="120" frameX="-0" frameY="-80" frameWidth="200" frameHeight="200"/>
  <SubTexture name="load0110" x="574" y="812" width="200" height="135" frameX="-0" frameY="-65" frameWidth="200" frameHeight="200"/>
  <SubTexture name="load0111" x="1318" y="336" width="200" height="152" frameX="-0" frameY="-48" frameWidth="200" frameHeight="200"/>
  <SubTexture name="load0112" x="1600" y="0" width="200" height="168" frameX="-0" frameY="-32" frameWidth="200" frameHeight="200"/>
  <SubTexture name="load0113" x="200" y="0" width="200" height="184" frameX="-0" frameY="-16" frameWidth="200" frameHeight="200"/>
  <SubTexture name="load0114" x="0" y="0" width="200" height="200" frameX="-0" frameY="-0" frameWidth="200" frameHeight="200"/>
  <SubTexture name="load0115" x="200" y="0" width="200" height="184" frameX="-0" frameY="-0" frameWidth="200" frameHeight="200"/>
  <SubTexture name="load0116" x="1600" y="0" width="200" height="168" frameX="-0" frameY="-0" frameWidth="200" frameHeight="200"/>
  <SubTexture name="load0117" x="1318" y="336" width="200" height="152" frameX="-0" frameY="-0" frameWidth="200" frameHeight="200"/>
  <SubTexture name="load0118" x="574" y="812" width="200" height="135" frameX="-0" frameY="-0" frameWidth="200" frameHeight="200"/>
  <SubTexture name="load0119" x="0" y="962" width="200" height="120" frameX="-0" frameY="-0" frameWidth="200" frameHeight="200"/>
  <SubTexture name="load0120" x="200" y="1077" width="200" height="104" frameX="-0" frameY="-0" frameWidth="200" frameHeight="200"/>
  <SubTexture name="load0121" x="1508" y="1290" width="200" height="88" frameX="-0" frameY="-0" frameWidth="200" frameHeight="200"/>
  <SubTexture name="load0122" x="1174" y="1462" width="200" height="73" frameX="-0" frameY="-0" frameWidth="200" frameHeight="200"/>
  <SubTexture name="load0123" x="1984" y="1635" width="200" height="56" frameX="-0" frameY="-0" frameWidth="200" frameHeight="200"/>
  <SubTexture name="load0124" x="1352" y="1853" width="200" height="40" frameX="-0" frameY="-0" frameWidth="200" frameHeight="200"/>
  <SubTexture name="load0125" x="87" y="1877" width="200" height="26" frameX="-0" frameY="-0" frameWidth="200" frameHeight="200"/>
  <SubTexture name="load0126" x="1829" y="1886" width="200" height="10" frameX="-0" frameY="-0" frameWidth="200" frameHeight="200"/>
  <SubTexture name="load0127" x="397" y="184" width="1" height="1" frameX="-0" frameY="-0" frameWidth="200" frameHeight="200"/>
  <SubTexture name="load0128" x="337" y="866" width="17" height="37" frameX="-0" frameY="-83" frameWidth="200" frameHeight="200"/>
  <SubTexture name="load0129" x="2141" y="992" width="58" height="51" frameX="-15" frameY="-70" frameWidth="200" frameHeight="200"/>
  <SubTexture name="load0130" x="921" y="1435" width="62" height="51" frameX="-69" frameY="-70" frameWidth="200" frameHeight="200"/>
  <SubTexture name="load0131" x="119" y="1294" width="63" height="51" frameX="-124" frameY="-71" frameWidth="200" frameHeight="200"/>
  <SubTexture name="load0132" x="354" y="866" width="17" height="32" frameX="-183" frameY="-89" frameWidth="200" frameHeight="200"/>
  <SubTexture name="load0133" x="397" y="184" width="1" height="1" frameX="-0" frameY="-0" frameWidth="200" frameHeight="200"/>
  <SubTexture name="load0134" x="2137" y="783" width="24" height="4" frameX="-44" frameY="-196" frameWidth="200" frameHeight="200"/>
  <SubTexture name="load0135" x="2063" y="783" width="36" height="13" frameX="-38" frameY="-187" frameWidth="200" frameHeight="200"/>
  <SubTexture name="load0136" x="337" y="814" width="36" height="28" frameX="-38" frameY="-172" frameWidth="200" frameHeight="200"/>
  <SubTexture name="load0137" x="1816" y="811" width="46" height="43" frameX="-32" frameY="-157" frameWidth="200" frameHeight="200"/>
  <SubTexture name="load0138" x="2110" y="272" width="80" height="61" frameX="-21" frameY="-139" frameWidth="200" frameHeight="200"/>
  <SubTexture name="load0139" x="1374" y="1386" width="92" height="72" frameX="-14" frameY="-128" frameWidth="200" frameHeight="200"/>
  <SubTexture name="load0140" x="0" y="1852" width="87" height="87" frameX="-14" frameY="-113" frameWidth="200" frameHeight="200"/>
  <SubTexture name="load0141" x="0" y="1752" width="90" height="100" frameX="-13" frameY="-98" frameWidth="200" frameHeight="200"/>
  <SubTexture name="load0142" x="1189" y="1648" width="92" height="104" frameX="-12" frameY="-86" frameWidth="200" frameHeight="200"/>
  <SubTexture name="load0143" x="2067" y="1691" width="87" height="104" frameX="-12" frameY="-80" frameWidth="200" frameHeight="200"/>
  <SubTexture name="load0144" x="1946" y="1290" width="90" height="104" frameX="-13" frameY="-75" frameWidth="200" frameHeight="200"/>
  <SubTexture name="load0145" x="1189" y="1648" width="92" height="104" frameX="-12" frameY="-72" frameWidth="200" frameHeight="200"/>
  <SubTexture name="load0146" x="1265" y="1776" width="87" height="100" frameX="-12" frameY="-73" frameWidth="200" frameHeight="200"/>
  <SubTexture name="load0147" x="182" y="1781" width="90" height="96" frameX="-12" frameY="-73" frameWidth="200" frameHeight="200"/>
  <SubTexture name="load0148" x="811" y="1770" width="92" height="95" frameX="-11" frameY="-73" frameWidth="200" frameHeight="200"/>
  <SubTexture name="load0149" x="1121" y="1816" width="87" height="94" frameX="-11" frameY="-74" frameWidth="200" frameHeight="200"/>
  <SubTexture name="load0150" x="612" y="1798" width="90" height="92" frameX="-12" frameY="-76" frameWidth="200" frameHeight="200"/>
  <SubTexture name="load0151" x="1991" y="1795" width="92" height="91" frameX="-11" frameY="-77" frameWidth="200" frameHeight="200"/>
  <SubTexture name="load0152" x="990" y="1821" width="87" height="91" frameX="-11" frameY="-77" frameWidth="200" frameHeight="200"/>
  <SubTexture name="load0153" x="1739" y="1815" width="90" height="91" frameX="-12" frameY="-77" frameWidth="200" frameHeight="200"/>
  <SubTexture name="load0154" x="1223" y="1294" width="92" height="92" frameX="-11" frameY="-76" frameWidth="200" frameHeight="200"/>
  <SubTexture name="load0155" x="1121" y="1816" width="87" height="94" frameX="-11" frameY="-74" frameWidth="200" frameHeight="200"/>
  <SubTexture name="load0156" x="272" y="1781" width="90" height="95" frameX="-12" frameY="-73" frameWidth="200" frameHeight="200"/>
  <SubTexture name="load0157" x="520" y="1761" width="92" height="96" frameX="-11" frameY="-72" frameWidth="200" frameHeight="200"/>
  <SubTexture name="load0158" x="1265" y="1776" width="87" height="100" frameX="-11" frameY="-68" frameWidth="200" frameHeight="200"/>
  <SubTexture name="load0159" x="2110" y="168" width="90" height="104" frameX="-12" frameY="-64" frameWidth="200" frameHeight="200"/>
  <SubTexture name="load0160" x="0" y="1648" width="92" height="104" frameX="-11" frameY="-64" frameWidth="200" frameHeight="200"/>
  <SubTexture name="load0161" x="2067" y="1691" width="87" height="104" frameX="-11" frameY="-64" frameWidth="200" frameHeight="200"/>
  <SubTexture name="load0162" x="2110" y="168" width="90" height="104" frameX="-12" frameY="-64" frameWidth="200" frameHeight="200"/>
  <SubTexture name="load0163" x="1523" y="1686" width="92" height="100" frameX="-11" frameY="-68" frameWidth="200" frameHeight="200"/>
  <SubTexture name="load0164" x="2083" y="1795" width="87" height="96" frameX="-11" frameY="-72" frameWidth="200" frameHeight="200"/>
  <SubTexture name="load0165" x="272" y="1781" width="90" height="95" frameX="-12" frameY="-73" frameWidth="200" frameHeight="200"/>
  <SubTexture name="load0166" x="90" y="1779" width="92" height="94" frameX="-11" frameY="-74" frameWidth="200" frameHeight="200"/>
  <SubTexture name="load0167" x="903" y="1821" width="87" height="92" frameX="-11" frameY="-76" frameWidth="200" frameHeight="200"/>
  <SubTexture name="load0168" x="889" y="1669" width="92" height="101" frameX="-10" frameY="-67" frameWidth="200" frameHeight="200"/>
  <SubTexture name="load0169" x="1430" y="1648" width="93" height="101" frameX="-10" frameY="-67" frameWidth="200" frameHeight="200"/>
  <SubTexture name="load0170" x="1546" y="1558" width="99" height="128" frameX="-5" frameY="-40" frameWidth="200" frameHeight="200"/>
  <SubTexture name="load0171" x="0" y="1294" width="119" height="144" frameX="-0" frameY="-24" frameWidth="200" frameHeight="200"/>
  <SubTexture name="load0172" x="917" y="1291" width="119" height="144" frameX="-0" frameY="-24" frameWidth="200" frameHeight="200"/>
  <SubTexture name="load0173" x="798" y="1291" width="119" height="144" frameX="-0" frameY="-24" frameWidth="200" frameHeight="200"/>
  <SubTexture name="load0174" x="0" y="1294" width="119" height="144" frameX="-0" frameY="-24" frameWidth="200" frameHeight="200"/>
  <SubTexture name="load0175" x="917" y="1291" width="119" height="144" frameX="-0" frameY="-24" frameWidth="200" frameHeight="200"/>
  <SubTexture name="load0176" x="798" y="1291" width="119" height="144" frameX="-0" frameY="-24" frameWidth="200" frameHeight="200"/>
  <SubTexture name="load0177" x="1742" y="1600" width="93" height="113" frameX="-12" frameY="-55" frameWidth="200" frameHeight="200"/>
  <SubTexture name="load0178" x="2016" y="992" width="125" height="152" frameX="-0" frameY="-16" frameWidth="200" frameHeight="200"/>
  <SubTexture name="load0179" x="784" y="1525" width="100" height="128" frameX="-5" frameY="-40" frameWidth="200" frameHeight="200"/>
  <SubTexture name="load0180" x="679" y="1291" width="119" height="144" frameX="-0" frameY="-24" frameWidth="200" frameHeight="200"/>
  <SubTexture name="load0181" x="1827" y="1290" width="119" height="144" frameX="-0" frameY="-24" frameWidth="200" frameHeight="200"/>
  <SubTexture name="load0182" x="1708" y="1290" width="119" height="144" frameX="-0" frameY="-24" frameWidth="200" frameHeight="200"/>
  <SubTexture name="load0183" x="679" y="1291" width="119" height="144" frameX="-0" frameY="-24" frameWidth="200" frameHeight="200"/>
  <SubTexture name="load0184" x="1827" y="1290" width="119" height="144" frameX="-0" frameY="-24" frameWidth="200" frameHeight="200"/>
  <SubTexture name="load0185" x="1708" y="1290" width="119" height="144" frameX="-0" frameY="-24" frameWidth="200" frameHeight="200"/>
  <SubTexture name="load0186" x="1645" y="1600" width="97" height="127" frameX="-12" frameY="-41" frameWidth="200" frameHeight="200"/>
  <SubTexture name="load0187" x="2066" y="336" width="125" height="152" frameX="-0" frameY="-16" frameWidth="200" frameHeight="200"/>
  <SubTexture name="load0188" x="2053" y="1507" width="104" height="128" frameX="-5" frameY="-40" frameWidth="200" frameHeight="200"/>
  <SubTexture name="load0189" x="2037" y="1288" width="119" height="144" frameX="-0" frameY="-24" frameWidth="200" frameHeight="200"/>
  <SubTexture name="load0190" x="560" y="1190" width="119" height="144" frameX="-0" frameY="-24" frameWidth="200" frameHeight="200"/>
  <SubTexture name="load0191" x="2037" y="1144" width="119" height="144" frameX="-0" frameY="-24" frameWidth="200" frameHeight="200"/>
  <SubTexture name="load0192" x="2037" y="1288" width="119" height="144" frameX="-0" frameY="-24" frameWidth="200" frameHeight="200"/>
  <SubTexture name="load0193" x="560" y="1190" width="119" height="144" frameX="-0" frameY="-24" frameWidth="200" frameHeight="200"/>
  <SubTexture name="load0194" x="2037" y="1144" width="119" height="144" frameX="-0" frameY="-24" frameWidth="200" frameHeight="200"/>
  <SubTexture name="load0195" x="362" y="1815" width="90" height="91" frameX="-12" frameY="-77" frameWidth="200" frameHeight="200"/>
  <SubTexture name="load0196" x="1899" y="1793" width="92" height="91" frameX="-11" frameY="-77" frameWidth="200" frameHeight="200"/>
  <SubTexture name="load0197" x="990" y="1821" width="87" height="91" frameX="-11" frameY="-77" frameWidth="200" frameHeight="200"/>
  <SubTexture name="load0198" x="612" y="1798" width="90" height="92" frameX="-12" frameY="-76" frameWidth="200" frameHeight="200"/>
  <SubTexture name="load0199" x="90" y="1779" width="92" height="94" frameX="-11" frameY="-74" frameWidth="200" frameHeight="200"/>
  <SubTexture name="load0200" x="702" y="1798" width="87" height="95" frameX="-11" frameY="-73" frameWidth="200" frameHeight="200"/>
  <SubTexture name="load0201" x="182" y="1781" width="90" height="96" frameX="-12" frameY="-72" frameWidth="200" frameHeight="200"/>
  <SubTexture name="load0202" x="1523" y="1686" width="92" height="100" frameX="-11" frameY="-68" frameWidth="200" frameHeight="200"/>
  <SubTexture name="load0203" x="1424" y="1749" width="87" height="104" frameX="-11" frameY="-64" frameWidth="200" frameHeight="200"/>
  <SubTexture name="load0204" x="1946" y="1290" width="90" height="104" frameX="-12" frameY="-64" frameWidth="200" frameHeight="200"/>
  <SubTexture name="load0205" x="0" y="1648" width="92" height="104" frameX="-11" frameY="-64" frameWidth="200" frameHeight="200"/>
  <SubTexture name="load0206" x="1424" y="1749" width="87" height="104" frameX="-11" frameY="-64" frameWidth="200" frameHeight="200"/>
  <SubTexture name="load0207" x="0" y="1752" width="90" height="100" frameX="-12" frameY="-68" frameWidth="200" frameHeight="200"/>
  <SubTexture name="load0208" x="520" y="1761" width="92" height="96" frameX="-11" frameY="-72" frameWidth="200" frameHeight="200"/>
  <SubTexture name="load0209" x="702" y="1798" width="87" height="95" frameX="-11" frameY="-73" frameWidth="200" frameHeight="200"/>
  <SubTexture name="load0210" x="1649" y="1791" width="90" height="94" frameX="-12" frameY="-74" frameWidth="200" frameHeight="200"/>
  <SubTexture name="load0211" x="1223" y="1294" width="92" height="92" frameX="-11" frameY="-76" frameWidth="200" frameHeight="200"/>
  <SubTexture name="load0212" x="559" y="1334" width="98" height="96" frameX="-0" frameY="-72" frameWidth="200" frameHeight="200"/>
  <SubTexture name="load0213" x="1977" y="1691" width="90" height="102" frameX="-12" frameY="-66" frameWidth="200" frameHeight="200"/>
  <SubTexture name="load0214" x="2063" y="683" width="123" height="100" frameX="-11" frameY="-68" frameWidth="200" frameHeight="200"/>
  <SubTexture name="load0215" x="1703" y="336" width="176" height="168" frameX="-11" frameY="-0" frameWidth="200" frameHeight="200"/>
  <SubTexture name="load0216" x="800" y="168" width="188" height="168" frameX="-12" frameY="-0" frameWidth="200" frameHeight="200"/>
  <SubTexture name="load0217" x="1549" y="168" width="187" height="168" frameX="-11" frameY="-0" frameWidth="200" frameHeight="200"/>
  <SubTexture name="load0218" x="1362" y="168" width="187" height="168" frameX="-11" frameY="-0" frameWidth="200" frameHeight="200"/>
  <SubTexture name="load0219" x="1518" y="336" width="185" height="161" frameX="-12" frameY="-7" frameWidth="200" frameHeight="200"/>
  <SubTexture name="load0220" x="574" y="947" width="187" height="137" frameX="-11" frameY="-31" frameWidth="200" frameHeight="200"/>
  <SubTexture name="load0221" x="1104" y="964" width="187" height="121" frameX="-11" frameY="-47" frameWidth="200" frameHeight="200"/>
  <SubTexture name="load0222" x="186" y="1287" width="186" height="103" frameX="-12" frameY="-65" frameWidth="200" frameHeight="200"/>
  <SubTexture name="load0223" x="372" y="1295" width="187" height="90" frameX="-11" frameY="-78" frameWidth="200" frameHeight="200"/>
  <SubTexture name="load0224" x="1508" y="1378" width="188" height="88" frameX="-11" frameY="-80" frameWidth="200" frameHeight="200"/>
  <SubTexture name="load0225" x="372" y="1385" width="186" height="87" frameX="-12" frameY="-81" frameWidth="200" frameHeight="200"/>
  <SubTexture name="load0226" x="1036" y="1294" width="187" height="91" frameX="-11" frameY="-77" frameWidth="200" frameHeight="200"/>
  <SubTexture name="load0227" x="1321" y="1290" width="187" height="96" frameX="-11" frameY="-72" frameWidth="200" frameHeight="200"/>
  <SubTexture name="load0228" x="374" y="1190" width="186" height="105" frameX="-12" frameY="-63" frameWidth="200" frameHeight="200"/>
  <SubTexture name="load0229" x="1828" y="1078" width="187" height="106" frameX="-11" frameY="-62" frameWidth="200" frameHeight="200"/>
  <SubTexture name="load0230" x="0" y="1082" width="187" height="106" frameX="-11" frameY="-62" frameWidth="200" frameHeight="200"/>
  <SubTexture name="load0231" x="0" y="1188" width="186" height="106" frameX="-12" frameY="-62" frameWidth="200" frameHeight="200"/>
  <SubTexture name="load0232" x="1291" y="1082" width="187" height="106" frameX="-11" frameY="-62" frameWidth="200" frameHeight="200"/>
  <SubTexture name="load0233" x="761" y="1083" width="187" height="106" frameX="-11" frameY="-62" frameWidth="200" frameHeight="200"/>
  <SubTexture name="load0234" x="1665" y="1184" width="186" height="106" frameX="-12" frameY="-62" frameWidth="200" frameHeight="200"/>
  <SubTexture name="load0235" x="1641" y="1078" width="187" height="106" frameX="-11" frameY="-62" frameWidth="200" frameHeight="200"/>
  <SubTexture name="load0236" x="537" y="1084" width="187" height="106" frameX="-11" frameY="-62" frameWidth="200" frameHeight="200"/>
  <SubTexture name="load0237" x="1851" y="1184" width="186" height="106" frameX="-12" frameY="-62" frameWidth="200" frameHeight="200"/>
  <SubTexture name="load0238" x="948" y="1085" width="187" height="106" frameX="-11" frameY="-62" frameWidth="200" frameHeight="200"/>
  <SubTexture name="load0239" x="187" y="1181" width="187" height="106" frameX="-11" frameY="-62" frameWidth="200" frameHeight="200"/>
  <SubTexture name="load0240" x="1135" y="1188" width="186" height="106" frameX="-12" frameY="-62" frameWidth="200" frameHeight="200"/>
  <SubTexture name="load0241" x="1828" y="1078" width="187" height="106" frameX="-11" frameY="-62" frameWidth="200" frameHeight="200"/>
  <SubTexture name="load0242" x="1478" y="1184" width="187" height="106" frameX="-11" frameY="-62" frameWidth="200" frameHeight="200"/>
  <SubTexture name="load0243" x="0" y="1188" width="186" height="106" frameX="-12" frameY="-62" frameWidth="200" frameHeight="200"/>
  <SubTexture name="load0244" x="1291" y="1082" width="187" height="106" frameX="-11" frameY="-62" frameWidth="200" frameHeight="200"/>
  <SubTexture name="load0245" x="761" y="1083" width="187" height="106" frameX="-11" frameY="-62" frameWidth="200" frameHeight="200"/>
  <SubTexture name="load0246" x="1665" y="1184" width="186" height="106" frameX="-12" frameY="-62" frameWidth="200" frameHeight="200"/>
  <SubTexture name="load0247" x="1641" y="1078" width="187" height="106" frameX="-11" frameY="-62" frameWidth="200" frameHeight="200"/>
  <SubTexture name="load0248" x="537" y="1084" width="187" height="106" frameX="-11" frameY="-62" frameWidth="200" frameHeight="200"/>
  <SubTexture name="load0249" x="1132" y="336" width="186" height="168" frameX="-12" frameY="-0" frameWidth="200" frameHeight="200"/>
  <SubTexture name="load0250" x="387" y="336" width="187" height="168" frameX="-11" frameY="-0" frameWidth="200" frameHeight="200"/>
  <SubTexture name="load0251" x="0" y="200" width="187" height="168" frameX="-11" frameY="-0" frameWidth="200" frameHeight="200"/>
  <SubTexture name="load0252" x="760" y="336" width="186" height="168" frameX="-12" frameY="-0" frameWidth="200" frameHeight="200"/>
  <SubTexture name="load0253" x="1923" y="168" width="187" height="168" frameX="-11" frameY="-0" frameWidth="200" frameHeight="200"/>
  <SubTexture name="load0254" x="200" y="184" width="187" height="168" frameX="-11" frameY="-0" frameWidth="200" frameHeight="200"/>
  <SubTexture name="load0255" x="574" y="336" width="186" height="168" frameX="-12" frameY="-0" frameWidth="200" frameHeight="200"/>
  <SubTexture name="load0256" x="1175" y="168" width="187" height="168" frameX="-11" frameY="-0" frameWidth="200" frameHeight="200"/>
  <SubTexture name="load0257" x="988" y="168" width="187" height="168" frameX="-11" frameY="-0" frameWidth="200" frameHeight="200"/>
  <SubTexture name="load0258" x="946" y="336" width="186" height="168" frameX="-12" frameY="-0" frameWidth="200" frameHeight="200"/>
  <SubTexture name="load0259" x="1736" y="168" width="187" height="168" frameX="-11" frameY="-0" frameWidth="200" frameHeight="200"/>
  <SubTexture name="load0260" x="187" y="507" width="187" height="154" frameX="-11" frameY="-14" frameWidth="200" frameHeight="200"/>
  <SubTexture name="load0261" x="1879" y="491" width="186" height="155" frameX="-12" frameY="-13" frameWidth="200" frameHeight="200"/>
  <SubTexture name="load0262" x="1690" y="504" width="187" height="154" frameX="-11" frameY="-14" frameWidth="200" frameHeight="200"/>
  <SubTexture name="load0263" x="0" y="677" width="187" height="153" frameX="-11" frameY="-15" frameWidth="200" frameHeight="200"/>
  <SubTexture name="load0264" x="374" y="658" width="186" height="154" frameX="-12" frameY="-14" frameWidth="200" frameHeight="200"/>
  <SubTexture name="load0265" x="0" y="368" width="187" height="155" frameX="-11" frameY="-13" frameWidth="200" frameHeight="200"/>
  <SubTexture name="load0266" x="1496" y="652" width="186" height="154" frameX="-12" frameY="-14" frameWidth="200" frameHeight="200"/>
  <SubTexture name="load0267" x="1682" y="658" width="187" height="153" frameX="-11" frameY="-15" frameWidth="200" frameHeight="200"/>
  <SubTexture name="load0268" x="748" y="504" width="187" height="154" frameX="-11" frameY="-14" frameWidth="200" frameHeight="200"/>
  <SubTexture name="load0269" x="1504" y="497" width="186" height="155" frameX="-12" frameY="-13" frameWidth="200" frameHeight="200"/>
  <SubTexture name="load0270" x="1690" y="504" width="187" height="154" frameX="-11" frameY="-14" frameWidth="200" frameHeight="200"/>
  <SubTexture name="load0271" x="1118" y="658" width="187" height="153" frameX="-11" frameY="-15" frameWidth="200" frameHeight="200"/>
  <SubTexture name="load0272" x="374" y="658" width="186" height="154" frameX="-12" frameY="-14" frameWidth="200" frameHeight="200"/>
  <SubTexture name="load0273" x="0" y="368" width="187" height="155" frameX="-11" frameY="-13" frameWidth="200" frameHeight="200"/>
  <SubTexture name="load0274" x="1122" y="504" width="187" height="154" frameX="-11" frameY="-14" frameWidth="200" frameHeight="200"/>
  <SubTexture name="load0275" x="1118" y="811" width="186" height="153" frameX="-12" frameY="-15" frameWidth="200" frameHeight="200"/>
  <SubTexture name="load0276" x="187" y="507" width="187" height="154" frameX="-11" frameY="-14" frameWidth="200" frameHeight="200"/>
  <SubTexture name="load0277" x="1879" y="336" width="187" height="155" frameX="-11" frameY="-13" frameWidth="200" frameHeight="200"/>
  <SubTexture name="load0278" x="560" y="658" width="186" height="154" frameX="-12" frameY="-14" frameWidth="200" frameHeight="200"/>
  <SubTexture name="load0279" x="1118" y="658" width="187" height="153" frameX="-11" frameY="-15" frameWidth="200" frameHeight="200"/>
  <SubTexture name="load0280" x="748" y="504" width="187" height="154" frameX="-11" frameY="-14" frameWidth="200" frameHeight="200"/>
  <SubTexture name="load0281" x="746" y="658" width="186" height="154" frameX="-12" frameY="-14" frameWidth="200" frameHeight="200"/>
  <SubTexture name="load0282" x="1869" y="800" width="187" height="153" frameX="-11" frameY="-15" frameWidth="200" frameHeight="200"/>
  <SubTexture name="load0283" x="935" y="504" width="187" height="154" frameX="-11" frameY="-14" frameWidth="200" frameHeight="200"/>
  <SubTexture name="load0284" x="1318" y="488" width="186" height="155" frameX="-12" frameY="-13" frameWidth="200" frameHeight="200"/>
  <SubTexture name="load0285" x="561" y="504" width="187" height="154" frameX="-11" frameY="-14" frameWidth="200" frameHeight="200"/>
  <SubTexture name="load0286" x="1305" y="797" width="187" height="153" frameX="-11" frameY="-15" frameWidth="200" frameHeight="200"/>
  <SubTexture name="load0287" x="1877" y="646" width="186" height="154" frameX="-12" frameY="-14" frameWidth="200" frameHeight="200"/>
  <SubTexture name="load0288" x="374" y="504" width="187" height="154" frameX="-11" frameY="-14" frameWidth="200" frameHeight="200"/>
  <SubTexture name="load0289" x="187" y="661" width="187" height="153" frameX="-11" frameY="-15" frameWidth="200" frameHeight="200"/>
  <SubTexture name="load0290" x="932" y="658" width="186" height="154" frameX="-12" frameY="-14" frameWidth="200" frameHeight="200"/>
  <SubTexture name="load0291" x="187" y="352" width="187" height="155" frameX="-11" frameY="-13" frameWidth="200" frameHeight="200"/>
  <SubTexture name="load0292" x="1309" y="643" width="187" height="154" frameX="-11" frameY="-14" frameWidth="200" frameHeight="200"/>
  <SubTexture name="load0293" x="1492" y="806" width="186" height="153" frameX="-12" frameY="-15" frameWidth="200" frameHeight="200"/>
  <SubTexture name="load0294" x="0" y="523" width="187" height="154" frameX="-11" frameY="-14" frameWidth="200" frameHeight="200"/>
  <SubTexture name="load0295" x="1800" y="0" width="200" height="168" frameX="-0" frameY="-0" frameWidth="200" frameHeight="200"/>
  <SubTexture name="load0296" x="600" y="0" width="200" height="168" frameX="-0" frameY="-0" frameWidth="200" frameHeight="200"/>
  <SubTexture name="load0297" x="800" y="0" width="200" height="168" frameX="-0" frameY="-0" frameWidth="200" frameHeight="200"/>
  <SubTexture name="load0298" x="1400" y="0" width="200" height="168" frameX="-0" frameY="-0" frameWidth="200" frameHeight="200"/>
  <SubTexture name="load0299" x="400" y="0" width="200" height="168" frameX="-0" frameY="-0" frameWidth="200" frameHeight="200"/>
  <SubTexture name="load0300" x="1200" y="0" width="200" height="168" frameX="-0" frameY="-0" frameWidth="200" frameHeight="200"/>
  <SubTexture name="load0301" x="1000" y="0" width="200" height="168" frameX="-0" frameY="-0" frameWidth="200" frameHeight="200"/>
  <SubTexture name="load0302" x="600" y="168" width="200" height="168" frameX="-0" frameY="-0" frameWidth="200" frameHeight="200"/>
  <SubTexture name="load0303" x="400" y="168" width="200" height="168" frameX="-0" frameY="-0" frameWidth="200" frameHeight="200"/>
  <SubTexture name="load0304" x="2000" y="0" width="200" height="168" frameX="-0" frameY="-0" frameWidth="200" frameHeight="200"/>
  <SubTexture name="load0305" x="1600" y="0" width="200" height="168" frameX="-0" frameY="-0" frameWidth="200" frameHeight="200"/>
  <SubTexture name="load0306" x="200" y="0" width="200" height="184" frameX="-0" frameY="-0" frameWidth="200" frameHeight="200"/>
  <SubTexture name="load0307" x="0" y="0" width="200" height="200" frameX="-0" frameY="-0" frameWidth="200" frameHeight="200"/>
  <SubTexture name="load0308" x="200" y="0" width="200" height="184" frameX="-0" frameY="-16" frameWidth="200" frameHeight="200"/>
  <SubTexture name="load0309" x="1600" y="0" width="200" height="168" frameX="-0" frameY="-32" frameWidth="200" frameHeight="200"/>
  <SubTexture name="load0310" x="1318" y="336" width="200" height="152" frameX="-0" frameY="-48" frameWidth="200" frameHeight="200"/>
  <SubTexture name="load0311" x="574" y="812" width="200" height="135" frameX="-0" frameY="-65" frameWidth="200" frameHeight="200"/>
  <SubTexture name="load0312" x="0" y="962" width="200" height="120" frameX="-0" frameY="-80" frameWidth="200" frameHeight="200"/>
  <SubTexture name="load0313" x="200" y="1077" width="200" height="104" frameX="-0" frameY="-96" frameWidth="200" frameHeight="200"/>
  <SubTexture name="load0314" x="1508" y="1290" width="200" height="88" frameX="-0" frameY="-112" frameWidth="200" frameHeight="200"/>
  <SubTexture name="load0315" x="1946" y="1432" width="200" height="75" frameX="-0" frameY="-125" frameWidth="200" frameHeight="200"/>
  <SubTexture name="load0316" x="119" y="1390" width="200" height="76" frameX="-0" frameY="-124" frameWidth="200" frameHeight="200"/>
  <SubTexture name="load0317" x="1696" y="1434" width="200" height="75" frameX="-0" frameY="-125" frameWidth="200" frameHeight="200"/>
  <SubTexture name="load0318" x="558" y="1435" width="200" height="75" frameX="-0" frameY="-125" frameWidth="200" frameHeight="200"/>
  <SubTexture name="load0319" x="1174" y="1386" width="200" height="76" frameX="-0" frameY="-124" frameWidth="200" frameHeight="200"/>
</TextureAtlas>