<gloveuniverse>
	<!--Rarity: 0=common, 1=uncommon, 2=rare-->
	<prizes>
		<prize id="1" asset="prize_balloon" rarity="0" count="0"/>
		<prize id="2" asset="prize_gloveglove" rarity="0" count="0" />
		<prize id="3" asset="prize_hat" rarity="0" count="0" />
		<prize id="11" asset="prize_garyballoon" rarity="0" count="0" />
		
		<prize id="4" asset="prize_flashlight" rarity="1" count="0" />
		<prize id="5" asset="prize_bubble" rarity="1" count="0" />
		<prize id="6" asset="prize_seabear" rarity="1" count="0" />
		<prize id="10" asset="prize_clownbot" rarity="1" count="0" />
		
		<prize id="9" asset="prize_comic" rarity="2" count="0" />
		<prize id="14" asset="prize_piratehat" rarity="2" count="0" />
		<prize id="13" asset="prize_shellphone" rarity="2" count="0" />
		
		<prize id="7" asset="prize_bb" rarity="3" count="0" />
		<prize id="8" asset="prize_mm" rarity="3" count="0" />
		<prize id="12" asset="prize_mr" rarity="3" count="0" />
	</prizes>
</gloveuniverse>